jstruct/__init__.py
jstruct/types.py
jstruct/utils.py
jstruct-2021.11.dist-info/LICENSE
jstruct-2021.11.dist-info/METADATA
jstruct-2021.11.dist-info/WHEEL
jstruct-2021.11.dist-info/top_level.txt
jstruct-2021.11.dist-info/RECORD
