Metadata-Version: 2.1
Name: jstruct
Version: 2021.11
Summary: Readable serializable and deserializable Python nested models
Home-page: https://github.com/purplship/jstruct
Author: DanielK
Author-email: danielk.developer@gmail.com
License: MIT
Platform: UNKNOWN
Classifier: Programming Language :: Python :: 3
Classifier: License :: OSI Approved :: MIT License
Classifier: Operating System :: OS Independent
Requires-Dist: attrs
